[
  {
    "id": "mem_1770285267838_cjia8bvhl",
    "type": "procedural",
    "category": "animation_pattern",
    "content": {
      "name": "Premium Fade In",
      "type": "entrance",
      "elements": [
        {
          "property": "opacity",
          "from": 0,
          "to": 1,
          "delay": 0,
          "duration": 20,
          "easing": "power2.out"
        },
        {
          "property": "y",
          "from": 30,
          "to": 0,
          "delay": 0,
          "duration": 25,
          "easing": "expo.out"
        }
      ],
      "timing": {
        "totalDuration": 25,
        "staggerDelay": 3,
        "staggerFrom": "start",
        "overlap": 0.2
      },
      "easing": {
        "primary": "expo.out",
        "category": "cinematic"
      },
      "tags": [
        "premium",
        "fade",
        "entrance",
        "professional"
      ],
      "id": "motion_1770285267838_lie3mp965",
      "successScore": 0.8,
      "usageCount": 0,
      "lastUsed": 0,
      "createdAt": 1770285267838
    },
    "metadata": {
      "timestamp": 1770285267838,
      "importance": "high",
      "accessCount": 1,
      "lastAccessed": 1770285267876,
      "tags": [
        "animation",
        "pattern",
        "entrance",
        "premium",
        "fade",
        "entrance",
        "professional"
      ]
    },
    "embedding": [
      0,
      0,
      0,
      0.28942984211696865,
      0.07235746052924216,
      0,
      0,
      0,
      0,
      0.07235746052924216,
      0.2170723815877265,
      0.07235746052924216,
      0,
      0,
      0.2170723815877265,
      0,
      0,
      0.07235746052924216,
      0,
      0,
      0,
      0.2170723815877265,
      0,
      0,
      0,
      0.07235746052924216,
      0.07235746052924216,
      0.14471492105848432,
      0,
      0.07235746052924216,
      0,
      0,
      0,
      0,
      0.07235746052924216,
      0,
      0,
      0.07235746052924216,
      0,
      0.07235746052924216,
      0.07235746052924216,
      0.2170723815877265,
      0.14471492105848432,
      0.14471492105848432,
      0.14471492105848432,
      0.07235746052924216,
      0,
      0,
      0.5788596842339373,
      0.07235746052924216,
      0.28942984211696865,
      0.14471492105848432,
      0,
      0.07235746052924216,
      0.07235746052924216,
      0,
      0.07235746052924216,
      0.14471492105848432,
      0.07235746052924216,
      0.14471492105848432,
      0.14471492105848432,
      0.07235746052924216,
      0.2170723815877265,
      0
    ]
  },
  {
    "id": "mem_1770285267839_jselryyh0",
    "type": "procedural",
    "category": "animation_pattern",
    "content": {
      "name": "Logo Reveal",
      "type": "reveal",
      "elements": [
        {
          "property": "scale",
          "from": 0.8,
          "to": 1,
          "delay": 0,
          "duration": 30,
          "easing": "back.out(1.7)"
        },
        {
          "property": "opacity",
          "from": 0,
          "to": 1,
          "delay": 0,
          "duration": 20,
          "easing": "power2.out"
        },
        {
          "property": "blur",
          "from": 10,
          "to": 0,
          "delay": 5,
          "duration": 20,
          "easing": "power2.out"
        }
      ],
      "timing": {
        "totalDuration": 35,
        "staggerDelay": 0,
        "staggerFrom": "start",
        "overlap": 0.5
      },
      "easing": {
        "primary": "back.out(1.7)",
        "category": "bouncy"
      },
      "tags": [
        "logo",
        "reveal",
        "brand",
        "impact"
      ],
      "id": "motion_1770285267839_zw2dhy8sg",
      "successScore": 0.8,
      "usageCount": 0,
      "lastUsed": 0,
      "createdAt": 1770285267839
    },
    "metadata": {
      "timestamp": 1770285267839,
      "importance": "high",
      "accessCount": 1,
      "lastAccessed": 1770285267876,
      "tags": [
        "animation",
        "pattern",
        "reveal",
        "logo",
        "reveal",
        "brand",
        "impact"
      ]
    },
    "embedding": [
      0,
      0,
      0,
      0.16929979439493012,
      0,
      0,
      0,
      0.05643326479831003,
      0,
      0.05643326479831003,
      0.11286652959662007,
      0.05643326479831003,
      0,
      0,
      0.22573305919324013,
      0,
      0,
      0.05643326479831003,
      0,
      0,
      0,
      0.22573305919324013,
      0,
      0,
      0,
      0.05643326479831003,
      0,
      0.16929979439493012,
      0,
      0.05643326479831003,
      0,
      0.11286652959662007,
      0,
      0,
      0.11286652959662007,
      0,
      0.05643326479831003,
      0,
      0,
      0.16929979439493012,
      0.05643326479831003,
      0.05643326479831003,
      0.16929979439493012,
      0.28216632399155017,
      0.16929979439493012,
      0.05643326479831003,
      0,
      0,
      0.5643326479831003,
      0.22573305919324013,
      0.05643326479831003,
      0.28216632399155017,
      0,
      0.16929979439493012,
      0.05643326479831003,
      0.11286652959662007,
      0.11286652959662007,
      0.05643326479831003,
      0.11286652959662007,
      0.16929979439493012,
      0,
      0,
      0.22573305919324013,
      0
    ]
  },
  {
    "id": "mem_1770285267839_ncdocqdny",
    "type": "procedural",
    "category": "animation_pattern",
    "content": {
      "name": "Staggered Text Reveal",
      "type": "entrance",
      "elements": [
        {
          "property": "opacity",
          "from": 0,
          "to": 1,
          "delay": 0,
          "duration": 15,
          "easing": "power2.out"
        },
        {
          "property": "y",
          "from": 40,
          "to": 0,
          "delay": 0,
          "duration": 20,
          "easing": "expo.out"
        }
      ],
      "timing": {
        "totalDuration": 45,
        "staggerDelay": 4,
        "staggerFrom": "start",
        "overlap": 0.3
      },
      "easing": {
        "primary": "expo.out",
        "category": "smooth"
      },
      "tags": [
        "text",
        "stagger",
        "reveal",
        "typography"
      ],
      "id": "motion_1770285267839_kf3raswwu",
      "successScore": 0.8,
      "usageCount": 0,
      "lastUsed": 0,
      "createdAt": 1770285267839
    },
    "metadata": {
      "timestamp": 1770285267839,
      "importance": "high",
      "accessCount": 1,
      "lastAccessed": 1770285267876,
      "tags": [
        "animation",
        "pattern",
        "entrance",
        "text",
        "stagger",
        "reveal",
        "typography"
      ]
    },
    "embedding": [
      0,
      0.07352146220938077,
      0,
      0.14704292441876154,
      0.07352146220938077,
      0,
      0,
      0,
      0,
      0.07352146220938077,
      0.14704292441876154,
      0.07352146220938077,
      0.07352146220938077,
      0,
      0.22056438662814232,
      0,
      0,
      0.14704292441876154,
      0.07352146220938077,
      0.07352146220938077,
      0,
      0.22056438662814232,
      0,
      0,
      0,
      0.07352146220938077,
      0,
      0.22056438662814232,
      0,
      0,
      0,
      0,
      0,
      0,
      0.07352146220938077,
      0,
      0.07352146220938077,
      0,
      0,
      0,
      0.07352146220938077,
      0.07352146220938077,
      0.14704292441876154,
      0.14704292441876154,
      0.14704292441876154,
      0.22056438662814232,
      0,
      0,
      0.5881716976750462,
      0.07352146220938077,
      0.22056438662814232,
      0.2940858488375231,
      0.07352146220938077,
      0.07352146220938077,
      0.07352146220938077,
      0,
      0.07352146220938077,
      0.14704292441876154,
      0.07352146220938077,
      0.14704292441876154,
      0.07352146220938077,
      0,
      0.22056438662814232,
      0
    ]
  },
  {
    "id": "mem_1770285267839_xiaqxdw4y",
    "type": "procedural",
    "category": "animation_pattern",
    "content": {
      "name": "Dramatic Scale",
      "type": "emphasis",
      "elements": [
        {
          "property": "scale",
          "from": 1,
          "to": 1.2,
          "delay": 0,
          "duration": 10,
          "easing": "power4.out"
        },
        {
          "property": "scale",
          "from": 1.2,
          "to": 1,
          "delay": 10,
          "duration": 15,
          "easing": "elastic.out(1, 0.5)"
        }
      ],
      "timing": {
        "totalDuration": 25,
        "staggerDelay": 0,
        "staggerFrom": "start",
        "overlap": 0
      },
      "easing": {
        "primary": "power4.out",
        "secondary": "elastic.out(1, 0.5)",
        "category": "dramatic"
      },
      "tags": [
        "scale",
        "emphasis",
        "impact",
        "attention"
      ],
      "id": "motion_1770285267839_gafv9r6yh",
      "successScore": 0.8,
      "usageCount": 0,
      "lastUsed": 0,
      "createdAt": 1770285267839
    },
    "metadata": {
      "timestamp": 1770285267839,
      "importance": "high",
      "accessCount": 1,
      "lastAccessed": 1770285267876,
      "tags": [
        "animation",
        "pattern",
        "emphasis",
        "scale",
        "emphasis",
        "impact",
        "attention"
      ]
    },
    "embedding": [
      0,
      0,
      0,
      0.17928429140015903,
      0,
      0,
      0,
      0,
      0,
      0.05976143046671968,
      0.2988071523335984,
      0.11952286093343936,
      0.05976143046671968,
      0,
      0.23904572186687872,
      0,
      0,
      0.05976143046671968,
      0,
      0,
      0,
      0.17928429140015903,
      0,
      0,
      0,
      0.05976143046671968,
      0,
      0.17928429140015903,
      0,
      0,
      0,
      0.11952286093343936,
      0,
      0,
      0.11952286093343936,
      0,
      0.05976143046671968,
      0,
      0,
      0,
      0.05976143046671968,
      0.05976143046671968,
      0.11952286093343936,
      0.23904572186687872,
      0.11952286093343936,
      0.05976143046671968,
      0,
      0,
      0.47809144373375745,
      0.47809144373375745,
      0.17928429140015903,
      0,
      0,
      0.11952286093343936,
      0.05976143046671968,
      0,
      0.05976143046671968,
      0.17928429140015903,
      0.11952286093343936,
      0.11952286093343936,
      0.11952286093343936,
      0,
      0.11952286093343936,
      0
    ]
  },
  {
    "id": "mem_1770285267839_mvcuhi1ww",
    "type": "procedural",
    "category": "animation_pattern",
    "content": {
      "name": "Smooth Exit",
      "type": "exit",
      "elements": [
        {
          "property": "opacity",
          "from": 1,
          "to": 0,
          "delay": 0,
          "duration": 20,
          "easing": "power2.in"
        },
        {
          "property": "y",
          "from": 0,
          "to": -30,
          "delay": 0,
          "duration": 25,
          "easing": "power3.in"
        }
      ],
      "timing": {
        "totalDuration": 25,
        "staggerDelay": 2,
        "staggerFrom": "end",
        "overlap": 0.2
      },
      "easing": {
        "primary": "power3.in",
        "category": "smooth"
      },
      "tags": [
        "exit",
        "fade",
        "smooth",
        "departure"
      ],
      "id": "motion_1770285267839_ihxon28aq",
      "successScore": 0.8,
      "usageCount": 0,
      "lastUsed": 0,
      "createdAt": 1770285267839
    },
    "metadata": {
      "timestamp": 1770285267839,
      "importance": "high",
      "accessCount": 1,
      "lastAccessed": 1770285267876,
      "tags": [
        "animation",
        "pattern",
        "exit",
        "exit",
        "fade",
        "smooth",
        "departure"
      ]
    },
    "embedding": [
      0,
      0,
      0,
      0.28005601680560194,
      0,
      0,
      0,
      0,
      0,
      0.07001400420140048,
      0.07001400420140048,
      0.07001400420140048,
      0.07001400420140048,
      0,
      0,
      0,
      0,
      0.07001400420140048,
      0.21004201260420147,
      0,
      0,
      0.21004201260420147,
      0,
      0,
      0,
      0.07001400420140048,
      0,
      0.28005601680560194,
      0,
      0.07001400420140048,
      0.21004201260420147,
      0.07001400420140048,
      0,
      0,
      0,
      0,
      0,
      0.21004201260420147,
      0,
      0,
      0.07001400420140048,
      0.07001400420140048,
      0.14002800840280097,
      0.14002800840280097,
      0.14002800840280097,
      0.07001400420140048,
      0,
      0,
      0.5601120336112039,
      0.07001400420140048,
      0.3500700210070024,
      0.07001400420140048,
      0,
      0.07001400420140048,
      0.07001400420140048,
      0,
      0.07001400420140048,
      0.14002800840280097,
      0.07001400420140048,
      0.14002800840280097,
      0.07001400420140048,
      0,
      0.21004201260420147,
      0
    ]
  },
  {
    "id": "mem_1770285267839_wq8ecr7xb",
    "type": "procedural",
    "category": "animation_pattern",
    "content": {
      "name": "Cinematic Camera Push",
      "type": "camera",
      "elements": [],
      "timing": {
        "totalDuration": 60,
        "staggerDelay": 0,
        "staggerFrom": "start",
        "overlap": 0
      },
      "easing": {
        "primary": "power2.inOut",
        "category": "cinematic"
      },
      "camera": {
        "type": "dolly",
        "intensity": 0.5,
        "startFrame": 0,
        "duration": 60,
        "easing": "power2.inOut"
      },
      "tags": [
        "camera",
        "dolly",
        "push",
        "cinematic"
      ],
      "id": "motion_1770285267839_7oin7njkc",
      "successScore": 0.8,
      "usageCount": 0,
      "lastUsed": 0,
      "createdAt": 1770285267839
    },
    "metadata": {
      "timestamp": 1770285267839,
      "importance": "high",
      "accessCount": 1,
      "lastAccessed": 1770285267876,
      "tags": [
        "animation",
        "pattern",
        "camera",
        "camera",
        "dolly",
        "push",
        "cinematic"
      ]
    },
    "embedding": [
      0,
      0.07559289460184544,
      0,
      0,
      0,
      0,
      0,
      0,
      0,
      0.22677868380553634,
      0.07559289460184544,
      0.07559289460184544,
      0,
      0,
      0.15118578920369088,
      0,
      0,
      0.07559289460184544,
      0,
      0,
      0,
      0.15118578920369088,
      0,
      0,
      0,
      0.07559289460184544,
      0.15118578920369088,
      0.5291502622129182,
      0,
      0,
      0,
      0,
      0,
      0,
      0.07559289460184544,
      0,
      0,
      0,
      0,
      0,
      0.07559289460184544,
      0.07559289460184544,
      0,
      0,
      0.07559289460184544,
      0.07559289460184544,
      0,
      0,
      0.5291502622129182,
      0,
      0.07559289460184544,
      0.22677868380553634,
      0,
      0.15118578920369088,
      0.07559289460184544,
      0,
      0.07559289460184544,
      0.07559289460184544,
      0.30237157840738177,
      0,
      0,
      0.22677868380553634,
      0.15118578920369088,
      0
    ]
  },
  {
    "id": "mem_1770285267839_i4pajq3dt",
    "type": "procedural",
    "category": "animation_pattern",
    "content": {
      "name": "Bouncy Pop In",
      "type": "entrance",
      "elements": [
        {
          "property": "scale",
          "from": 0,
          "to": 1,
          "delay": 0,
          "duration": 30,
          "easing": "elastic.out(1, 0.5)"
        },
        {
          "property": "opacity",
          "from": 0,
          "to": 1,
          "delay": 0,
          "duration": 10,
          "easing": "power2.out"
        }
      ],
      "timing": {
        "totalDuration": 35,
        "staggerDelay": 5,
        "staggerFrom": "center",
        "overlap": 0.3
      },
      "easing": {
        "primary": "elastic.out(1, 0.5)",
        "category": "bouncy"
      },
      "tags": [
        "bounce",
        "pop",
        "fun",
        "playful"
      ],
      "id": "motion_1770285267839_7q28mss7x",
      "successScore": 0.8,
      "usageCount": 0,
      "lastUsed": 0,
      "createdAt": 1770285267839
    },
    "metadata": {
      "timestamp": 1770285267839,
      "importance": "high",
      "accessCount": 1,
      "lastAccessed": 1770285267876,
      "tags": [
        "animation",
        "pattern",
        "entrance",
        "bounce",
        "pop",
        "fun",
        "playful"
      ]
    },
    "embedding": [
      0,
      0,
      0,
      0.1257389226923863,
      0,
      0,
      0,
      0,
      0,
      0.06286946134619315,
      0.18860838403857944,
      0.06286946134619315,
      0,
      0,
      0.18860838403857944,
      0,
      0,
      0.18860838403857944,
      0,
      0,
      0,
      0.18860838403857944,
      0,
      0,
      0,
      0.06286946134619315,
      0,
      0.18860838403857944,
      0,
      0.06286946134619315,
      0,
      0.1257389226923863,
      0,
      0,
      0.06286946134619315,
      0,
      0.1257389226923863,
      0.06286946134619315,
      0,
      0,
      0.06286946134619315,
      0.06286946134619315,
      0.1257389226923863,
      0.3143473067309657,
      0.1257389226923863,
      0.06286946134619315,
      0,
      0,
      0.6286946134619315,
      0.2514778453847726,
      0.06286946134619315,
      0.1257389226923863,
      0,
      0.2514778453847726,
      0.06286946134619315,
      0.06286946134619315,
      0.1257389226923863,
      0.06286946134619315,
      0.06286946134619315,
      0.1257389226923863,
      0,
      0,
      0.1257389226923863,
      0.06286946134619315
    ]
  },
  {
    "id": "mem_1770285267839_6ef68voou",
    "type": "procedural",
    "category": "animation_pattern",
    "content": {
      "name": "Slide From Left",
      "type": "entrance",
      "elements": [
        {
          "property": "x",
          "from": -100,
          "to": 0,
          "delay": 0,
          "duration": 25,
          "easing": "expo.out"
        },
        {
          "property": "opacity",
          "from": 0,
          "to": 1,
          "delay": 0,
          "duration": 15,
          "easing": "power2.out"
        }
      ],
      "timing": {
        "totalDuration": 25,
        "staggerDelay": 3,
        "staggerFrom": "start",
        "overlap": 0.2
      },
      "easing": {
        "primary": "expo.out",
        "category": "snappy"
      },
      "tags": [
        "slide",
        "left",
        "entrance",
        "direction"
      ],
      "id": "motion_1770285267839_j05zi4rhx",
      "successScore": 0.8,
      "usageCount": 0,
      "lastUsed": 0,
      "createdAt": 1770285267839
    },
    "metadata": {
      "timestamp": 1770285267839,
      "importance": "high",
      "accessCount": 1,
      "lastAccessed": 1770285267876,
      "tags": [
        "animation",
        "pattern",
        "entrance",
        "slide",
        "left",
        "entrance",
        "direction"
      ]
    },
    "embedding": [
      0,
      0.13968605915391563,
      0,
      0.27937211830783126,
      0,
      0,
      0,
      0.13968605915391563,
      0,
      0.06984302957695782,
      0.20952908873087345,
      0.06984302957695782,
      0,
      0,
      0.20952908873087345,
      0,
      0,
      0.06984302957695782,
      0,
      0,
      0,
      0.20952908873087345,
      0,
      0,
      0,
      0.06984302957695782,
      0,
      0.20952908873087345,
      0,
      0,
      0,
      0,
      0,
      0,
      0.06984302957695782,
      0,
      0.06984302957695782,
      0,
      0,
      0,
      0.06984302957695782,
      0.06984302957695782,
      0.20952908873087345,
      0.13968605915391563,
      0.13968605915391563,
      0.13968605915391563,
      0,
      0,
      0.5587442366156625,
      0.27937211830783126,
      0.27937211830783126,
      0.13968605915391563,
      0,
      0.06984302957695782,
      0.06984302957695782,
      0,
      0.13968605915391563,
      0.06984302957695782,
      0.06984302957695782,
      0.13968605915391563,
      0,
      0,
      0.13968605915391563,
      0
    ]
  },
  {
    "id": "mem_1770285267840_wxlhokdsh",
    "type": "procedural",
    "category": "animation_pattern",
    "content": {
      "name": "Impact Shake",
      "type": "emphasis",
      "elements": [
        {
          "property": "x",
          "from": 0,
          "to": 5,
          "delay": 0,
          "duration": 2,
          "easing": "none"
        },
        {
          "property": "x",
          "from": 5,
          "to": -5,
          "delay": 2,
          "duration": 2,
          "easing": "none"
        },
        {
          "property": "x",
          "from": -5,
          "to": 3,
          "delay": 4,
          "duration": 2,
          "easing": "none"
        },
        {
          "property": "x",
          "from": 3,
          "to": 0,
          "delay": 6,
          "duration": 4,
          "easing": "power2.out"
        }
      ],
      "timing": {
        "totalDuration": 10,
        "staggerDelay": 0,
        "staggerFrom": "start",
        "overlap": 0
      },
      "easing": {
        "primary": "none",
        "category": "snappy"
      },
      "camera": {
        "type": "shake",
        "intensity": 0.3,
        "startFrame": 0,
        "duration": 10,
        "easing": "power2.out"
      },
      "tags": [
        "shake",
        "impact",
        "emphasis",
        "camera"
      ],
      "id": "motion_1770285267840_jb5pczssb",
      "successScore": 0.8,
      "usageCount": 0,
      "lastUsed": 0,
      "createdAt": 1770285267840
    },
    "metadata": {
      "timestamp": 1770285267840,
      "importance": "high",
      "accessCount": 1,
      "lastAccessed": 1770285267876,
      "tags": [
        "animation",
        "pattern",
        "emphasis",
        "shake",
        "impact",
        "emphasis",
        "camera"
      ]
    },
    "embedding": [
      0,
      0,
      0,
      0.18333969940564226,
      0,
      0,
      0.1375047745542317,
      0,
      0,
      0.045834924851410566,
      0.045834924851410566,
      0.045834924851410566,
      0,
      0,
      0.09166984970282113,
      0,
      0,
      0.045834924851410566,
      0,
      0,
      0,
      0.2750095491084634,
      0,
      0,
      0,
      0.045834924851410566,
      0,
      0.18333969940564226,
      0,
      0,
      0,
      0.1375047745542317,
      0,
      0,
      0.045834924851410566,
      0,
      0,
      0,
      0,
      0,
      0.045834924851410566,
      0.045834924851410566,
      0.18333969940564226,
      0.18333969940564226,
      0.22917462425705284,
      0.09166984970282113,
      0,
      0,
      0.4583492485141057,
      0.045834924851410566,
      0.22917462425705284,
      0.2750095491084634,
      0.09166984970282113,
      0.22917462425705284,
      0.09166984970282113,
      0,
      0.4125143236626951,
      0.045834924851410566,
      0.18333969940564226,
      0.18333969940564226,
      0.09166984970282113,
      0,
      0.09166984970282113,
      0
    ]
  },
  {
    "id": "mem_1770285267840_pl2hcuunz",
    "type": "semantic",
    "category": "audio_scene_mapping",
    "content": {
      "sceneType": "intro",
      "audioType": "bgm",
      "mood": "epic",
      "characteristics": {
        "tempo": "medium",
        "energy": "high",
        "complexity": "moderate",
        "instruments": [
          "orchestra",
          "drums",
          "brass"
        ],
        "keywords": [
          "epic",
          "cinematic",
          "trailer",
          "powerful",
          "intro"
        ]
      },
      "examples": [],
      "id": "audio_1770285267840_cno7ppx0c",
      "successScore": 0.75,
      "usageCount": 0,
      "lastUsed": 0,
      "createdAt": 1770285267840
    },
    "metadata": {
      "timestamp": 1770285267840,
      "importance": "high",
      "accessCount": 6,
      "lastAccessed": 1770285267876,
      "tags": [
        "audio",
        "mapping",
        "intro",
        "bgm",
        "epic"
      ]
    },
    "embedding": [
      0,
      0,
      0.1259881576697424,
      0,
      0,
      0.2519763153394848,
      0.1259881576697424,
      0,
      0.2519763153394848,
      0.1259881576697424,
      0,
      0.1259881576697424,
      0,
      0.2519763153394848,
      0,
      0,
      0.1259881576697424,
      0.1259881576697424,
      0,
      0.1259881576697424,
      0,
      0,
      0,
      0,
      0.1259881576697424,
      0,
      0,
      0.3779644730092272,
      0,
      0,
      0.1259881576697424,
      0,
      0,
      0,
      0.1259881576697424,
      0,
      0,
      0,
      0,
      0,
      0,
      0,
      0.1259881576697424,
      0,
      0.3779644730092272,
      0.1259881576697424,
      0,
      0,
      0.3779644730092272,
      0.2519763153394848,
      0.1259881576697424,
      0,
      0,
      0,
      0,
      0.1259881576697424,
      0.1259881576697424,
      0,
      0,
      0,
      0,
      0.2519763153394848,
      0,
      0.1259881576697424
    ]
  },
  {
    "id": "mem_1770285267840_mjdufga1y",
    "type": "semantic",
    "category": "audio_scene_mapping",
    "content": {
      "sceneType": "intro",
      "audioType": "bgm",
      "mood": "tech",
      "characteristics": {
        "tempo": "medium",
        "energy": "medium",
        "complexity": "moderate",
        "instruments": [
          "synth",
          "electronic",
          "bass"
        ],
        "keywords": [
          "tech",
          "digital",
          "modern",
          "electronic",
          "futuristic"
        ]
      },
      "examples": [],
      "id": "audio_1770285267840_2q764yob0",
      "successScore": 0.75,
      "usageCount": 0,
      "lastUsed": 0,
      "createdAt": 1770285267840
    },
    "metadata": {
      "timestamp": 1770285267840,
      "importance": "high",
      "accessCount": 6,
      "lastAccessed": 1770285267876,
      "tags": [
        "audio",
        "mapping",
        "intro",
        "bgm",
        "tech"
      ]
    },
    "embedding": [
      0,
      0,
      0.2519763153394848,
      0.1259881576697424,
      0,
      0,
      0.1259881576697424,
      0,
      0.2519763153394848,
      0.1259881576697424,
      0,
      0.2519763153394848,
      0,
      0,
      0,
      0,
      0.1259881576697424,
      0.1259881576697424,
      0,
      0,
      0,
      0,
      0.2519763153394848,
      0,
      0.1259881576697424,
      0,
      0,
      0.3779644730092272,
      0,
      0,
      0.1259881576697424,
      0.1259881576697424,
      0,
      0.1259881576697424,
      0,
      0,
      0,
      0,
      0,
      0,
      0,
      0,
      0.1259881576697424,
      0,
      0.2519763153394848,
      0.1259881576697424,
      0,
      0,
      0.3779644730092272,
      0.1259881576697424,
      0.1259881576697424,
      0,
      0,
      0,
      0,
      0.1259881576697424,
      0.1259881576697424,
      0,
      0,
      0,
      0.3779644730092272,
      0.1259881576697424,
      0,
      0
    ]
  },
  {
    "id": "mem_1770285267841_4vua4zgyp",
    "type": "semantic",
    "category": "audio_scene_mapping",
    "content": {
      "sceneType": "logo",
      "audioType": "sfx",
      "mood": "epic",
      "characteristics": {
        "energy": "high",
        "keywords": [
          "impact",
          "logo",
          "reveal",
          "hit",
          "boom"
        ]
      },
      "examples": [],
      "id": "audio_1770285267841_1i7vzy8hw",
      "successScore": 0.75,
      "usageCount": 0,
      "lastUsed": 0,
      "createdAt": 1770285267841
    },
    "metadata": {
      "timestamp": 1770285267841,
      "importance": "high",
      "accessCount": 3,
      "lastAccessed": 1770285267876,
      "tags": [
        "audio",
        "mapping",
        "logo",
        "sfx",
        "epic"
      ]
    },
    "embedding": [
      0,
      0,
      0,
      0,
      0,
      0.2857142857142857,
      0.14285714285714285,
      0,
      0.14285714285714285,
      0.14285714285714285,
      0,
      0,
      0,
      0,
      0,
      0,
      0.14285714285714285,
      0.14285714285714285,
      0,
      0.14285714285714285,
      0,
      0,
      0,
      0,
      0,
      0,
      0,
      0.42857142857142855,
      0,
      0,
      0.14285714285714285,
      0,
      0,
      0,
      0.14285714285714285,
      0,
      0,
      0,
      0,
      0,
      0,
      0,
      0.14285714285714285,
      0.42857142857142855,
      0,
      0.14285714285714285,
      0,
      0,
      0.42857142857142855,
      0,
      0.2857142857142857,
      0.14285714285714285,
      0,
      0,
      0,
      0.14285714285714285,
      0.14285714285714285,
      0,
      0.14285714285714285,
      0,
      0,
      0,
      0,
      0
    ]
  },
  {
    "id": "mem_1770285267841_g9lz37i0b",
    "type": "semantic",
    "category": "audio_scene_mapping",
    "content": {
      "sceneType": "transition",
      "audioType": "sfx",
      "mood": "tech",
      "characteristics": {
        "energy": "medium",
        "keywords": [
          "whoosh",
          "transition",
          "sweep",
          "pass"
        ]
      },
      "examples": [],
      "id": "audio_1770285267841_8jxq4wnye",
      "successScore": 0.75,
      "usageCount": 0,
      "lastUsed": 0,
      "createdAt": 1770285267841
    },
    "metadata": {
      "timestamp": 1770285267841,
      "importance": "high",
      "accessCount": 2,
      "lastAccessed": 1770285267876,
      "tags": [
        "audio",
        "mapping",
        "transition",
        "sfx",
        "tech"
      ]
    },
    "embedding": [
      0,
      0,
      0,
      0,
      0,
      0.1543033499620919,
      0.1543033499620919,
      0,
      0.1543033499620919,
      0.1543033499620919,
      0,
      0.1543033499620919,
      0,
      0,
      0,
      0,
      0.1543033499620919,
      0.3086066999241838,
      0,
      0,
      0,
      0,
      0.3086066999241838,
      0,
      0,
      0,
      0,
      0.3086066999241838,
      0,
      0,
      0.1543033499620919,
      0,
      0,
      0,
      0,
      0,
      0,
      0,
      0,
      0,
      0,
      0,
      0.1543033499620919,
      0.3086066999241838,
      0.1543033499620919,
      0.1543033499620919,
      0,
      0,
      0.4629100498862757,
      0,
      0.3086066999241838,
      0,
      0,
      0,
      0,
      0.1543033499620919,
      0.1543033499620919,
      0,
      0.1543033499620919,
      0,
      0,
      0,
      0,
      0
    ]
  },
  {
    "id": "mem_1770285267841_v9sz3aam0",
    "type": "semantic",
    "category": "audio_scene_mapping",
    "content": {
      "sceneType": "content",
      "audioType": "bgm",
      "mood": "corporate",
      "characteristics": {
        "tempo": "medium",
        "energy": "medium",
        "complexity": "minimal",
        "instruments": [
          "piano",
          "strings",
          "acoustic"
        ],
        "keywords": [
          "corporate",
          "business",
          "professional",
          "clean",
          "modern"
        ]
      },
      "examples": [],
      "id": "audio_1770285267841_yu9d4r1xs",
      "successScore": 0.75,
      "usageCount": 0,
      "lastUsed": 0,
      "createdAt": 1770285267841
    },
    "metadata": {
      "timestamp": 1770285267841,
      "importance": "high",
      "accessCount": 4,
      "lastAccessed": 1770285267876,
      "tags": [
        "audio",
        "mapping",
        "content",
        "bgm",
        "corporate"
      ]
    },
    "embedding": [
      0.11547005383792514,
      0,
      0.11547005383792514,
      0,
      0,
      0,
      0.11547005383792514,
      0,
      0.23094010767585027,
      0.3464101615137754,
      0,
      0.23094010767585027,
      0,
      0,
      0,
      0,
      0.11547005383792514,
      0.11547005383792514,
      0,
      0,
      0,
      0,
      0,
      0,
      0,
      0,
      0,
      0.5773502691896257,
      0,
      0,
      0.11547005383792514,
      0,
      0,
      0.23094010767585027,
      0,
      0,
      0,
      0,
      0,
      0.11547005383792514,
      0,
      0,
      0.11547005383792514,
      0,
      0.11547005383792514,
      0.11547005383792514,
      0,
      0,
      0.3464101615137754,
      0.11547005383792514,
      0.23094010767585027,
      0,
      0,
      0,
      0,
      0.11547005383792514,
      0.11547005383792514,
      0.11547005383792514,
      0,
      0,
      0,
      0.11547005383792514,
      0.11547005383792514,
      0
    ]
  },
  {
    "id": "mem_1770285267841_ajayy9st2",
    "type": "semantic",
    "category": "audio_scene_mapping",
    "content": {
      "sceneType": "climax",
      "audioType": "bgm",
      "mood": "epic",
      "characteristics": {
        "tempo": "fast",
        "energy": "high",
        "complexity": "complex",
        "instruments": [
          "orchestra",
          "drums",
          "choir"
        ],
        "keywords": [
          "climax",
          "epic",
          "powerful",
          "dramatic",
          "peak"
        ]
      },
      "examples": [],
      "id": "audio_1770285267841_3orfi2wlf",
      "successScore": 0.75,
      "usageCount": 0,
      "lastUsed": 0,
      "createdAt": 1770285267841
    },
    "metadata": {
      "timestamp": 1770285267841,
      "importance": "high",
      "accessCount": 2,
      "lastAccessed": 1770285267876,
      "tags": [
        "audio",
        "mapping",
        "climax",
        "bgm",
        "epic"
      ]
    },
    "embedding": [
      0,
      0,
      0.12403473458920847,
      0,
      0,
      0.24806946917841693,
      0.12403473458920847,
      0,
      0.24806946917841693,
      0.12403473458920847,
      0,
      0,
      0,
      0.12403473458920847,
      0,
      0,
      0.12403473458920847,
      0.12403473458920847,
      0,
      0.24806946917841693,
      0,
      0,
      0,
      0,
      0.12403473458920847,
      0,
      0,
      0.3721042037676254,
      0.12403473458920847,
      0,
      0.12403473458920847,
      0.12403473458920847,
      0,
      0,
      0.24806946917841693,
      0,
      0,
      0,
      0,
      0,
      0,
      0,
      0.12403473458920847,
      0,
      0.12403473458920847,
      0.12403473458920847,
      0,
      0,
      0.49613893835683387,
      0,
      0.24806946917841693,
      0,
      0,
      0,
      0,
      0.12403473458920847,
      0.12403473458920847,
      0.12403473458920847,
      0,
      0,
      0.24806946917841693,
      0,
      0,
      0
    ]
  },
  {
    "id": "mem_1770285267841_3b3p2295v",
    "type": "semantic",
    "category": "audio_scene_mapping",
    "content": {
      "sceneType": "outro",
      "audioType": "bgm",
      "mood": "calm",
      "characteristics": {
        "tempo": "slow",
        "energy": "low",
        "complexity": "minimal",
        "instruments": [
          "piano",
          "strings",
          "pad"
        ],
        "keywords": [
          "outro",
          "ending",
          "calm",
          "resolve",
          "peaceful"
        ]
      },
      "examples": [],
      "id": "audio_1770285267841_krlpqu7t2",
      "successScore": 0.75,
      "usageCount": 0,
      "lastUsed": 0,
      "createdAt": 1770285267841
    },
    "metadata": {
      "timestamp": 1770285267841,
      "importance": "high",
      "accessCount": 1,
      "lastAccessed": 1770285267876,
      "tags": [
        "audio",
        "mapping",
        "outro",
        "bgm",
        "calm"
      ]
    },
    "embedding": [
      0,
      0.12403473458920847,
      0.12403473458920847,
      0,
      0,
      0,
      0.12403473458920847,
      0,
      0.24806946917841693,
      0.24806946917841693,
      0,
      0.24806946917841693,
      0,
      0,
      0,
      0,
      0.12403473458920847,
      0.12403473458920847,
      0,
      0.12403473458920847,
      0.12403473458920847,
      0,
      0,
      0,
      0,
      0.12403473458920847,
      0,
      0.3721042037676254,
      0,
      0,
      0.12403473458920847,
      0.24806946917841693,
      0,
      0.12403473458920847,
      0,
      0,
      0,
      0,
      0,
      0,
      0,
      0,
      0.12403473458920847,
      0,
      0.24806946917841693,
      0.12403473458920847,
      0,
      0,
      0.49613893835683387,
      0.12403473458920847,
      0.24806946917841693,
      0,
      0,
      0,
      0,
      0.12403473458920847,
      0.12403473458920847,
      0,
      0,
      0,
      0,
      0,
      0.12403473458920847,
      0
    ]
  },
  {
    "id": "mem_1770285267841_554c7qcmv",
    "type": "semantic",
    "category": "audio_scene_mapping",
    "content": {
      "sceneType": "content",
      "audioType": "ambience",
      "mood": "tech",
      "characteristics": {
        "energy": "low",
        "keywords": [
          "ambient",
          "digital",
          "drone",
          "atmosphere",
          "tech"
        ]
      },
      "examples": [],
      "id": "audio_1770285267841_61xwiazr8",
      "successScore": 0.75,
      "usageCount": 0,
      "lastUsed": 0,
      "createdAt": 1770285267841
    },
    "metadata": {
      "timestamp": 1770285267841,
      "importance": "high",
      "accessCount": 1,
      "lastAccessed": 1770285267876,
      "tags": [
        "audio",
        "mapping",
        "content",
        "ambience",
        "tech"
      ]
    },
    "embedding": [
      0,
      0,
      0.14907119849998599,
      0,
      0,
      0,
      0.14907119849998599,
      0,
      0.14907119849998599,
      0.14907119849998599,
      0,
      0,
      0,
      0,
      0,
      0,
      0.14907119849998599,
      0.14907119849998599,
      0,
      0,
      0.14907119849998599,
      0,
      0.29814239699997197,
      0,
      0.29814239699997197,
      0,
      0,
      0.29814239699997197,
      0,
      0,
      0.29814239699997197,
      0,
      0,
      0,
      0,
      0,
      0,
      0,
      0,
      0,
      0.14907119849998599,
      0,
      0.14907119849998599,
      0,
      0,
      0.14907119849998599,
      0,
      0,
      0.4472135954999579,
      0,
      0.29814239699997197,
      0,
      0,
      0,
      0,
      0.14907119849998599,
      0.29814239699997197,
      0.14907119849998599,
      0,
      0,
      0,
      0,
      0,
      0
    ]
  },
  {
    "id": "mem_1770285267841_d9ezj3578",
    "type": "procedural",
    "category": "sfx_pattern",
    "content": {
      "triggerType": "animation_start",
      "sfxType": "whoosh",
      "timing": {
        "offsetFrames": -2,
        "duration": 15,
        "fadeIn": 2,
        "fadeOut": 5
      },
      "id": "audio_1770285267841_3dibty06w",
      "successScore": 0.75,
      "usageCount": 0,
      "createdAt": 1770285267841
    },
    "metadata": {
      "timestamp": 1770285267841,
      "importance": "high",
      "accessCount": 2,
      "lastAccessed": 1770285267876,
      "tags": [
        "sfx",
        "pattern",
        "animation_start",
        "whoosh"
      ]
    },
    "embedding": [
      0,
      0,
      0,
      0,
      0,
      0,
      0,
      0,
      0,
      0,
      0,
      0,
      0,
      0,
      0.16222142113076254,
      0,
      0,
      0.16222142113076254,
      0,
      0,
      0.16222142113076254,
      0,
      0,
      0,
      0,
      0.16222142113076254,
      0,
      0.3244428422615251,
      0,
      0,
      0.16222142113076254,
      0.16222142113076254,
      0,
      0,
      0,
      0,
      0.16222142113076254,
      0,
      0,
      0,
      0,
      0,
      0,
      0,
      0.16222142113076254,
      0,
      0.16222142113076254,
      0,
      0.3244428422615251,
      0,
      0.6488856845230502,
      0,
      0,
      0.16222142113076254,
      0.16222142113076254,
      0,
      0,
      0.16222142113076254,
      0.16222142113076254,
      0,
      0,
      0,
      0,
      0.16222142113076254
    ]
  },
  {
    "id": "mem_1770285267841_qsp563g49",
    "type": "procedural",
    "category": "sfx_pattern",
    "content": {
      "triggerType": "impact",
      "sfxType": "impact",
      "timing": {
        "offsetFrames": -2,
        "duration": 30,
        "fadeIn": 0,
        "fadeOut": 10
      },
      "layering": {
        "primary": "impact",
        "secondary": "whoosh",
        "volumeRatio": 0.5,
        "offsetFrames": -5
      },
      "id": "audio_1770285267841_u7etevm9h",
      "successScore": 0.75,
      "usageCount": 0,
      "createdAt": 1770285267841
    },
    "metadata": {
      "timestamp": 1770285267841,
      "importance": "high",
      "accessCount": 1,
      "lastAccessed": 1770285267876,
      "tags": [
        "sfx",
        "pattern",
        "impact",
        "impact"
      ]
    },
    "embedding": [
      0,
      0,
      0,
      0,
      0,
      0,
      0,
      0,
      0,
      0,
      0,
      0,
      0.11785113019775793,
      0,
      0.11785113019775793,
      0.23570226039551587,
      0,
      0.11785113019775793,
      0,
      0,
      0,
      0,
      0,
      0,
      0,
      0,
      0,
      0.23570226039551587,
      0,
      0.11785113019775793,
      0.11785113019775793,
      0.23570226039551587,
      0,
      0,
      0,
      0,
      0,
      0,
      0,
      0,
      0,
      0,
      0,
      0,
      0.11785113019775793,
      0,
      0.11785113019775793,
      0,
      0.47140452079103173,
      0,
      0.3535533905932738,
      0,
      0,
      0.23570226039551587,
      0.11785113019775793,
      0,
      0,
      0.23570226039551587,
      0.47140452079103173,
      0,
      0.11785113019775793,
      0,
      0.11785113019775793,
      0.11785113019775793
    ]
  },
  {
    "id": "mem_1770285267841_rkzsiw7xk",
    "type": "procedural",
    "category": "sfx_pattern",
    "content": {
      "triggerType": "reveal",
      "sfxType": "reveal",
      "timing": {
        "offsetFrames": 0,
        "duration": 45,
        "fadeIn": 5,
        "fadeOut": 15
      },
      "id": "audio_1770285267841_c33hub7u7",
      "successScore": 0.75,
      "usageCount": 0,
      "createdAt": 1770285267841
    },
    "metadata": {
      "timestamp": 1770285267841,
      "importance": "high",
      "accessCount": 1,
      "lastAccessed": 1770285267876,
      "tags": [
        "sfx",
        "pattern",
        "reveal",
        "reveal"
      ]
    },
    "embedding": [
      0,
      0.17149858514250882,
      0,
      0,
      0,
      0,
      0,
      0,
      0,
      0,
      0,
      0,
      0,
      0,
      0.17149858514250882,
      0,
      0,
      0.17149858514250882,
      0,
      0,
      0,
      0,
      0,
      0,
      0,
      0,
      0,
      0.34299717028501764,
      0,
      0,
      0.17149858514250882,
      0.17149858514250882,
      0,
      0,
      0,
      0,
      0.17149858514250882,
      0,
      0,
      0,
      0,
      0,
      0,
      0,
      0.17149858514250882,
      0,
      0.17149858514250882,
      0.17149858514250882,
      0.5144957554275265,
      0,
      0.34299717028501764,
      0.34299717028501764,
      0,
      0.17149858514250882,
      0.17149858514250882,
      0,
      0,
      0.17149858514250882,
      0,
      0,
      0,
      0,
      0,
      0.17149858514250882
    ]
  },
  {
    "id": "mem_1770285267841_lqmz8cjob",
    "type": "procedural",
    "category": "sfx_pattern",
    "content": {
      "triggerType": "scene_change",
      "sfxType": "transition",
      "timing": {
        "offsetFrames": -3,
        "duration": 20,
        "fadeIn": 2,
        "fadeOut": 8
      },
      "id": "audio_1770285267841_hhgja87zz",
      "successScore": 0.75,
      "usageCount": 0,
      "createdAt": 1770285267841
    },
    "metadata": {
      "timestamp": 1770285267841,
      "importance": "high",
      "accessCount": 2,
      "lastAccessed": 1770285267876,
      "tags": [
        "sfx",
        "pattern",
        "scene_change",
        "transition"
      ]
    },
    "embedding": [
      0,
      0,
      0,
      0.17677669529663687,
      0,
      0,
      0,
      0,
      0,
      0,
      0,
      0,
      0,
      0,
      0.17677669529663687,
      0,
      0,
      0.17677669529663687,
      0,
      0,
      0,
      0,
      0,
      0,
      0,
      0.17677669529663687,
      0,
      0.35355339059327373,
      0,
      0,
      0.17677669529663687,
      0.17677669529663687,
      0,
      0,
      0,
      0,
      0,
      0,
      0,
      0,
      0,
      0,
      0,
      0.17677669529663687,
      0.17677669529663687,
      0,
      0.17677669529663687,
      0,
      0.35355339059327373,
      0,
      0.5303300858899106,
      0.17677669529663687,
      0,
      0,
      0.17677669529663687,
      0,
      0.17677669529663687,
      0.17677669529663687,
      0,
      0,
      0,
      0,
      0.17677669529663687,
      0.17677669529663687
    ]
  },
  {
    "id": "mem_1770285267841_xnrgk05w0",
    "type": "procedural",
    "category": "sfx_pattern",
    "content": {
      "triggerType": "transition",
      "sfxType": "whoosh",
      "timing": {
        "offsetFrames": -2,
        "duration": 12,
        "fadeIn": 1,
        "fadeOut": 5
      },
      "id": "audio_1770285267841_0tzz881su",
      "successScore": 0.75,
      "usageCount": 0,
      "createdAt": 1770285267841
    },
    "metadata": {
      "timestamp": 1770285267841,
      "importance": "high",
      "accessCount": 1,
      "lastAccessed": 1770285267876,
      "tags": [
        "sfx",
        "pattern",
        "transition",
        "whoosh"
      ]
    },
    "embedding": [
      0,
      0,
      0,
      0,
      0,
      0,
      0,
      0,
      0,
      0,
      0,
      0,
      0,
      0,
      0.17677669529663687,
      0,
      0,
      0.17677669529663687,
      0,
      0,
      0,
      0,
      0,
      0,
      0,
      0.17677669529663687,
      0,
      0.35355339059327373,
      0,
      0,
      0.17677669529663687,
      0.17677669529663687,
      0,
      0.17677669529663687,
      0,
      0,
      0,
      0,
      0,
      0,
      0,
      0,
      0,
      0.17677669529663687,
      0.17677669529663687,
      0,
      0.17677669529663687,
      0,
      0.35355339059327373,
      0.17677669529663687,
      0.5303300858899106,
      0,
      0,
      0.17677669529663687,
      0.17677669529663687,
      0,
      0,
      0.17677669529663687,
      0.17677669529663687,
      0,
      0,
      0,
      0,
      0.17677669529663687
    ]
  },
  {
    "id": "mem_1770285267843_1wnrp71t9",
    "type": "procedural",
    "category": "composition_template",
    "content": {
      "name": "Modern Logo Reveal",
      "description": "Clean, professional logo reveal with impact and glow effects",
      "videoType": "logo",
      "complexity": "simple",
      "structure": {
        "totalDuration": 150,
        "fps": 30,
        "width": 1920,
        "height": 1080,
        "aspectRatio": "16:9",
        "sceneCount": 1,
        "audioLayers": 2
      },
      "scenes": [
        {
          "id": "scene_logo",
          "name": "Logo Reveal",
          "type": "logo",
          "startFrame": 0,
          "endFrame": 150,
          "duration": 150,
          "elements": [
            {
              "type": "background",
              "layer": 0,
              "position": {
                "x": 0,
                "y": 0
              },
              "style": {
                "backgroundColor": "#0a0a0a"
              }
            },
            {
              "type": "logo",
              "layer": 1,
              "position": {
                "x": "50%",
                "y": "50%"
              },
              "size": {
                "width": "30%",
                "height": "auto"
              }
            }
          ],
          "animations": [
            {
              "targetElement": 1,
              "startFrame": 15,
              "endFrame": 45,
              "patternName": "Logo Reveal",
              "properties": {
                "scale": [
                  0.8,
                  1
                ],
                "opacity": [
                  0,
                  1
                ]
              }
            }
          ],
          "audio": [
            {
              "type": "sfx",
              "keywords": [
                "impact",
                "logo",
                "hit"
              ],
              "startFrame": 20,
              "duration": 30,
              "volume": 0.8
            }
          ],
          "effects": [
            {
              "type": "glow",
              "preset": "soft",
              "settings": {
                "color": "#6366F1",
                "intensity": 0.5
              },
              "startFrame": 25,
              "endFrame": 120
            },
            {
              "type": "vignette",
              "settings": {
                "intensity": 0.3
              },
              "startFrame": 0,
              "endFrame": 150
            }
          ],
          "camera": {
            "type": "dolly",
            "intensity": 0.3,
            "startFrame": 0,
            "endFrame": 60,
            "easing": "power2.out"
          }
        }
      ],
      "tags": [
        "logo",
        "reveal",
        "modern",
        "clean",
        "impact"
      ],
      "id": "template_1770285267843_avxs1dv9x",
      "successScore": 0.8,
      "usageCount": 0,
      "lastUsed": 0,
      "createdAt": 1770285267843
    },
    "metadata": {
      "timestamp": 1770285267843,
      "importance": "high",
      "accessCount": 2,
      "lastAccessed": 1770285267877,
      "tags": [
        "template",
        "composition",
        "logo",
        "simple",
        "logo",
        "reveal",
        "modern",
        "clean",
        "impact"
      ]
    },
    "embedding": [
      0,
      0.0607456739230787,
      0.03037283696153935,
      0.0607456739230787,
      0.03037283696153935,
      0.03037283696153935,
      0.09111851088461805,
      0,
      0.03037283696153935,
      0.09111851088461805,
      0.03037283696153935,
      0.0607456739230787,
      0.1214913478461574,
      0.09111851088461805,
      0.09111851088461805,
      0,
      0,
      0.09111851088461805,
      0.03037283696153935,
      0.0607456739230787,
      0,
      0.03037283696153935,
      0.03037283696153935,
      0.0607456739230787,
      0.03037283696153935,
      0.1214913478461574,
      0,
      0.1822370217692361,
      0,
      0.09111851088461805,
      0,
      0,
      0,
      0.09111851088461805,
      0.03037283696153935,
      0.09111851088461805,
      0.03037283696153935,
      0.0607456739230787,
      0.0607456739230787,
      0.03037283696153935,
      0.03037283696153935,
      0.09111851088461805,
      0.0607456739230787,
      0.27335553265385415,
      0.0607456739230787,
      0.03037283696153935,
      0,
      0.09111851088461805,
      0.4555925544230902,
      0.1822370217692361,
      0.21260985873077543,
      0.3948468805000115,
      0.03037283696153935,
      0.3341012065769328,
      0,
      0,
      0.15186418480769673,
      0.09111851088461805,
      0.3644740435384722,
      0,
      0,
      0,
      0.1214913478461574,
      0
    ]
  },
  {
    "id": "mem_1770285267843_5pbu4n8qn",
    "type": "procedural",
    "category": "composition_template",
    "content": {
      "name": "Tech Product Showcase",
      "description": "3-scene product showcase with tech aesthetic",
      "videoType": "promo",
      "complexity": "medium",
      "structure": {
        "totalDuration": 300,
        "fps": 30,
        "width": 1920,
        "height": 1080,
        "aspectRatio": "16:9",
        "sceneCount": 3,
        "audioLayers": 3
      },
      "scenes": [
        {
          "id": "scene_intro",
          "name": "Intro",
          "type": "intro",
          "startFrame": 0,
          "endFrame": 90,
          "duration": 90,
          "elements": [
            {
              "type": "background",
              "layer": 0,
              "position": {
                "x": 0,
                "y": 0
              },
              "style": {
                "background": "linear-gradient(135deg, #0a0a0f 0%, #1a1a2e 100%)"
              }
            },
            {
              "type": "text",
              "layer": 1,
              "position": {
                "x": "50%",
                "y": "50%"
              },
              "content": "INTRODUCING",
              "style": {
                "fontSize": "24px",
                "color": "#8B5CF6"
              }
            }
          ],
          "animations": [
            {
              "targetElement": 1,
              "startFrame": 10,
              "endFrame": 40,
              "patternName": "Premium Fade In",
              "properties": {}
            }
          ],
          "audio": [
            {
              "type": "bgm",
              "mood": "tech",
              "keywords": [
                "electronic",
                "modern"
              ],
              "startFrame": 0,
              "duration": 300,
              "volume": 0.4,
              "fadeIn": 30
            },
            {
              "type": "ambience",
              "keywords": [
                "digital",
                "atmosphere"
              ],
              "startFrame": 0,
              "duration": 300,
              "volume": 0.15
            }
          ],
          "effects": [],
          "camera": {
            "type": "crane",
            "intensity": 0.2,
            "startFrame": 0,
            "endFrame": 90,
            "easing": "power2.out"
          }
        },
        {
          "id": "scene_product",
          "name": "Product",
          "type": "content",
          "startFrame": 90,
          "endFrame": 210,
          "duration": 120,
          "elements": [
            {
              "type": "image",
              "layer": 1,
              "position": {
                "x": "50%",
                "y": "50%"
              },
              "size": {
                "width": "60%",
                "height": "auto"
              }
            }
          ],
          "animations": [
            {
              "targetElement": 0,
              "startFrame": 90,
              "endFrame": 120,
              "patternName": "Dramatic Scale",
              "properties": {}
            }
          ],
          "audio": [
            {
              "type": "sfx",
              "keywords": [
                "whoosh",
                "transition"
              ],
              "startFrame": 88,
              "duration": 15,
              "volume": 0.7
            }
          ],
          "effects": [
            {
              "type": "particle",
              "preset": "glow",
              "settings": {
                "count": 30,
                "color": "#6366F1"
              },
              "startFrame": 100,
              "endFrame": 200
            }
          ]
        },
        {
          "id": "scene_cta",
          "name": "CTA",
          "type": "outro",
          "startFrame": 210,
          "endFrame": 300,
          "duration": 90,
          "elements": [
            {
              "type": "text",
              "layer": 1,
              "position": {
                "x": "50%",
                "y": "40%"
              },
              "content": "Get Started",
              "style": {
                "fontSize": "48px",
                "fontWeight": "bold"
              }
            },
            {
              "type": "logo",
              "layer": 2,
              "position": {
                "x": "50%",
                "y": "70%"
              },
              "size": {
                "width": "15%",
                "height": "auto"
              }
            }
          ],
          "animations": [
            {
              "targetElement": 0,
              "startFrame": 215,
              "endFrame": 245,
              "patternName": "Staggered Text Reveal",
              "properties": {}
            },
            {
              "targetElement": 1,
              "startFrame": 235,
              "endFrame": 265,
              "patternName": "Premium Fade In",
              "properties": {}
            }
          ],
          "audio": [
            {
              "type": "sfx",
              "keywords": [
                "reveal",
                "shine"
              ],
              "startFrame": 220,
              "duration": 30,
              "volume": 0.6
            }
          ],
          "effects": []
        }
      ],
      "tags": [
        "tech",
        "product",
        "showcase",
        "modern",
        "promo"
      ],
      "id": "template_1770285267843_v4yl29wom",
      "successScore": 0.8,
      "usageCount": 0,
      "lastUsed": 0,
      "createdAt": 1770285267843
    },
    "metadata": {
      "timestamp": 1770285267843,
      "importance": "high",
      "accessCount": 2,
      "lastAccessed": 1770285267877,
      "tags": [
        "template",
        "composition",
        "promo",
        "medium",
        "tech",
        "product",
        "showcase",
        "modern",
        "promo"
      ]
    },
    "embedding": [
      0.01902778181530907,
      0.03805556363061814,
      0.03805556363061814,
      0.01902778181530907,
      0.03805556363061814,
      0.05708334544592721,
      0.09513890907654535,
      0.01902778181530907,
      0.05708334544592721,
      0.07611112726123628,
      0.03805556363061814,
      0.11416669089185442,
      0.05708334544592721,
      0.09513890907654535,
      0.01902778181530907,
      0.05708334544592721,
      0.05708334544592721,
      0.22833338178370885,
      0.03805556363061814,
      0.09513890907654535,
      0.01902778181530907,
      0.01902778181530907,
      0.17125003633778163,
      0.1331944727071635,
      0.05708334544592721,
      0.11416669089185442,
      0,
      0.266388945414327,
      0.01902778181530907,
      0.09513890907654535,
      0.01902778181530907,
      0.03805556363061814,
      0,
      0.05708334544592721,
      0,
      0.05708334544592721,
      0.05708334544592721,
      0.1331944727071635,
      0.09513890907654535,
      0,
      0.01902778181530907,
      0.15222225452247257,
      0.07611112726123628,
      0.05708334544592721,
      0.17125003633778163,
      0.09513890907654535,
      0,
      0.1331944727071635,
      0.3805556363061814,
      0.20930559996839976,
      0.2473611635990179,
      0.266388945414327,
      0.05708334544592721,
      0.34250007267556326,
      0.01902778181530907,
      0.03805556363061814,
      0.11416669089185442,
      0.20930559996839976,
      0.30444450904494513,
      0,
      0.09513890907654535,
      0,
      0.05708334544592721,
      0.01902778181530907
    ]
  },
  {
    "id": "mem_1770285267843_l6ft7let8",
    "type": "procedural",
    "category": "composition_template",
    "content": {
      "name": "Social Media Ad (15s)",
      "description": "Fast-paced 15-second social media ad",
      "videoType": "social",
      "complexity": "simple",
      "structure": {
        "totalDuration": 450,
        "fps": 30,
        "width": 1080,
        "height": 1920,
        "aspectRatio": "9:16",
        "sceneCount": 3,
        "audioLayers": 2
      },
      "scenes": [
        {
          "id": "scene_hook",
          "name": "Hook",
          "type": "intro",
          "startFrame": 0,
          "endFrame": 90,
          "duration": 90,
          "elements": [
            {
              "type": "text",
              "layer": 1,
              "position": {
                "x": "50%",
                "y": "50%"
              },
              "content": "STOP SCROLLING",
              "style": {
                "fontSize": "64px",
                "fontWeight": "black"
              }
            }
          ],
          "animations": [
            {
              "targetElement": 0,
              "startFrame": 5,
              "endFrame": 25,
              "patternName": "Bouncy Pop In",
              "properties": {}
            }
          ],
          "audio": [
            {
              "type": "bgm",
              "mood": "energetic",
              "keywords": [
                "upbeat",
                "trendy"
              ],
              "startFrame": 0,
              "duration": 450,
              "volume": 0.5
            },
            {
              "type": "sfx",
              "keywords": [
                "impact",
                "attention"
              ],
              "startFrame": 8,
              "duration": 20,
              "volume": 0.8
            }
          ],
          "effects": []
        },
        {
          "id": "scene_value",
          "name": "Value Prop",
          "type": "content",
          "startFrame": 90,
          "endFrame": 330,
          "duration": 240,
          "elements": [
            {
              "type": "text",
              "layer": 1,
              "position": {
                "x": "50%",
                "y": "30%"
              }
            },
            {
              "type": "image",
              "layer": 2,
              "position": {
                "x": "50%",
                "y": "60%"
              }
            }
          ],
          "animations": [],
          "audio": [
            {
              "type": "sfx",
              "keywords": [
                "whoosh"
              ],
              "startFrame": 88,
              "duration": 10,
              "volume": 0.6
            }
          ],
          "effects": []
        },
        {
          "id": "scene_cta",
          "name": "CTA",
          "type": "outro",
          "startFrame": 330,
          "endFrame": 450,
          "duration": 120,
          "elements": [
            {
              "type": "text",
              "layer": 1,
              "position": {
                "x": "50%",
                "y": "50%"
              },
              "content": "Link in Bio"
            }
          ],
          "animations": [],
          "audio": [],
          "effects": []
        }
      ],
      "tags": [
        "social",
        "vertical",
        "fast",
        "attention",
        "15s"
      ],
      "id": "template_1770285267843_37ednrh45",
      "successScore": 0.8,
      "usageCount": 0,
      "lastUsed": 0,
      "createdAt": 1770285267843
    },
    "metadata": {
      "timestamp": 1770285267843,
      "importance": "high",
      "accessCount": 2,
      "lastAccessed": 1770285267877,
      "tags": [
        "template",
        "composition",
        "social",
        "simple",
        "social",
        "vertical",
        "fast",
        "attention",
        "15s"
      ]
    },
    "embedding": [
      0.02853650727676748,
      0,
      0.05707301455353496,
      0.05707301455353496,
      0.05707301455353496,
      0.05707301455353496,
      0.05707301455353496,
      0.02853650727676748,
      0.05707301455353496,
      0.08560952183030245,
      0.02853650727676748,
      0.1426825363838374,
      0.02853650727676748,
      0.02853650727676748,
      0.02853650727676748,
      0.1426825363838374,
      0.11414602910706992,
      0.1712190436606049,
      0,
      0.11414602910706992,
      0,
      0,
      0.08560952183030245,
      0.11414602910706992,
      0.02853650727676748,
      0.08560952183030245,
      0,
      0.3424380873212098,
      0.05707301455353496,
      0.08560952183030245,
      0,
      0.02853650727676748,
      0,
      0,
      0.05707301455353496,
      0.11414602910706992,
      0.11414602910706992,
      0.11414602910706992,
      0.1426825363838374,
      0,
      0.02853650727676748,
      0.1426825363838374,
      0.08560952183030245,
      0,
      0.19975555093737235,
      0.11414602910706992,
      0.02853650727676748,
      0.1426825363838374,
      0.2568285654909073,
      0.1712190436606049,
      0.22829205821413984,
      0.08560952183030245,
      0.02853650727676748,
      0.3424380873212098,
      0.05707301455353496,
      0.02853650727676748,
      0.19975555093737235,
      0.22829205821413984,
      0.3995111018747447,
      0,
      0,
      0,
      0.1426825363838374,
      0.02853650727676748
    ]
  },
  {
    "id": "mem_1770285267844_h0ks0l150",
    "type": "episodic",
    "category": "action",
    "content": {
      "action": "Started project: 9af15938-b1f2-4e3d-ab41-b8f3804ba13b",
      "result": "success"
    },
    "metadata": {
      "timestamp": 1770285267844,
      "importance": "medium",
      "accessCount": 1,
      "lastAccessed": 1770285267876,
      "tags": [
        "action",
        "workflow"
      ],
      "projectId": "9af15938-b1f2-4e3d-ab41-b8f3804ba13b"
    },
    "embedding": [
      0,
      0,
      0.31622776601683794,
      0,
      0,
      0,
      0,
      0,
      0.31622776601683794,
      0,
      0.31622776601683794,
      0,
      0,
      0,
      0,
      0,
      0,
      0,
      0,
      0,
      0,
      0,
      0,
      0,
      0,
      0,
      0,
      0.31622776601683794,
      0,
      0,
      0.31622776601683794,
      0,
      0,
      0,
      0,
      0.31622776601683794,
      0.31622776601683794,
      0,
      0,
      0.31622776601683794,
      0,
      0,
      0,
      0,
      0,
      0,
      0,
      0,
      0,
      0,
      0,
      0,
      0,
      0,
      0,
      0,
      0,
      0,
      0,
      0,
      0,
      0.31622776601683794,
      0,
      0.31622776601683794
    ]
  }
]